dataio/__init__.py
dataio/cli/__init__.py
dataio/cli/cli.py
dataio/cli/user.py
dataio/sdk/__init__.py
dataio/sdk/admin.py
dataio/sdk/user.py
dataio_artpark-0.4.0b14.dist-info/METADATA
dataio_artpark-0.4.0b14.dist-info/WHEEL
dataio_artpark-0.4.0b14.dist-info/entry_points.txt
dataio_artpark-0.4.0b14.dist-info/licenses/LICENSE
dataio_artpark-0.4.0b14.dist-info/RECORD
