Metadata-Version: 2.4
Name: dataio-artpark
Version: 0.4.0b14
Summary: Postgres and FASTAPI based Dataset Management System (DMS), with a CLI and SDK for interacting with the API.
Project-URL: Homepage, https://dataio.artpark.ai
Project-URL: Github, https://github.com/dsih-artpark/dataio
Author-email: Akhil B <akhil@artpark.in>, Sneha S <sneha@artpark.in>
License-Expression: GPL-3.0-or-later
License-File: LICENSE
Requires-Python: >=3.12
Requires-Dist: pytest>=8.4.1
Requires-Dist: python-dotenv>=1.1.0
Requires-Dist: pyyaml>=6.0.2
Requires-Dist: requests>=2.32.4
Requires-Dist: tabulate>=0.9.0
Requires-Dist: typer>=0.16.0
